wangpancli/__init__.py
wangpancli/baidu_pan_sdk.py
wangpancli/base.py
wangpancli-0.1.1.dist-info/licenses/LICENSE
wangpancli-0.1.1.dist-info/METADATA
wangpancli-0.1.1.dist-info/WHEEL
wangpancli-0.1.1.dist-info/entry_points.txt
wangpancli-0.1.1.dist-info/top_level.txt
wangpancli-0.1.1.dist-info/RECORD
