Metadata-Version: 2.4
Name: wangpancli
Version: 0.1.1
Summary: cloud storage CLI (Command Line Interface)
Home-page: https://gitee.com/aierwiki/wangpancli
Author: Tang Yubin
Author-email: tang-yu-bin@qq.com
Classifier: Programming Language :: Python :: 3
Classifier: License :: OSI Approved :: MIT License
Classifier: Operating System :: OS Independent
Requires-Python: >=3.10.0
License-File: LICENSE
Requires-Dist: loguru>=0.7.2
Requires-Dist: requests>=2.32.3
Requires-Dist: rich>=13.7.0
Dynamic: author
Dynamic: author-email
Dynamic: classifier
Dynamic: description
Dynamic: description-content-type
Dynamic: home-page
Dynamic: license-file
Dynamic: requires-dist
Dynamic: requires-python
Dynamic: summary
